[
  {
    "directors": [
      "罗兰·艾默里奇"
    ],
    "rate": "7.9",
    "cover_x": 3365,
    "star": "40",
    "title": "2012",
    "url": "https://movie.douban.com/subject/3005875/",
    "casts": [
      "约翰·库萨克",
      "阿曼达·皮特",
      "切瓦特·埃加福",
      "坦迪·牛顿",
      "奥利弗·普莱特"
    ],
    "cover": "https://img1.doubanio.com/view/photo/s_ratio_poster/public/p505238859.jpg",
    "id": "3005875",
    "cover_y": 5000
  },
  {
    "directors": [
      "黄大瑟"
    ],
    "rate": "8.5",
    "cover_x": 560,
    "star": "45",
    "title": "你的目光所及之处",
    "url": "https://movie.douban.com/subject/35047667/",
    "casts": [
      "韩基灿",
      "张义秀",
      "崔呈媛",
      "郑西仁",
      "千昇豪"
    ],
    "cover": "https://img3.doubanio.com/view/photo/s_ratio_poster/public/p2599876441.jpg",
    "id": "35047667",
    "cover_y": 792
  },
  {
    "directors": [
      "盖·里奇"
    ],
    "rate": "7.5",
    "cover_x": 1900,
    "star": "40",
    "title": "阿拉丁",
    "url": "https://movie.douban.com/subject/26891256/",
    "casts": [
      "梅纳·玛索德",
      "娜奥米·斯科特",
      "威尔·史密斯",
      "马尔万·肯扎里",
      "纳维德·内加班"
    ],
    "cover": "https://img3.doubanio.com/view/photo/s_ratio_poster/public/p2553992741.jpg",
    "id": "26891256",
    "cover_y": 2715
  },
  {
    "directors": [
      "大卫·雷奇"
    ],
    "rate": "6.3",
    "cover_x": 1080,
    "star": "30",
    "title": "速度与激情：特别行动",
    "url": "https://movie.douban.com/subject/27163278/",
    "casts": [
      "道恩·强森",
      "杰森·斯坦森",
      "伊德里斯·艾尔巴",
      "凡妮莎·柯比",
      "艾莎·冈萨雷斯"
    ],
    "cover": "https://img3.doubanio.com/view/photo/s_ratio_poster/public/p2561542272.jpg",
    "id": "27163278",
    "cover_y": 1581
  },
  {
    "directors": [
      "李力持",
      "周星驰"
    ],
    "rate": "8.3",
    "cover_x": 1024,
    "star": "40",
    "title": "国产凌凌漆",
    "url": "https://movie.douban.com/subject/1307739/",
    "casts": [
      "周星驰",
      "袁咏仪",
      "罗家英",
      "陈宝莲",
      "郑祖"
    ],
    "cover": "https://img1.doubanio.com/view/photo/s_ratio_poster/public/p2585823759.jpg",
    "id": "1307739",
    "cover_y": 1515
  },
  {
    "directors": [
      "程小东"
    ],
    "rate": "7.9",
    "cover_x": 2000,
    "star": "40",
    "title": "倩女幽魂2：人间道",
    "url": "https://movie.douban.com/subject/1296629/",
    "casts": [
      "张国荣",
      "王祖贤",
      "张学友",
      "午马",
      "李子雄"
    ],
    "cover": "https://img9.doubanio.com/view/photo/s_ratio_poster/public/p2518212196.jpg",
    "id": "1296629",
    "cover_y": 3000
  },
  {
    "directors": [
      "科林·特雷沃罗"
    ],
    "rate": "7.7",
    "cover_x": 1400,
    "star": "40",
    "title": "侏罗纪世界",
    "url": "https://movie.douban.com/subject/10440138/",
    "casts": [
      "克里斯·帕拉特",
      "布莱丝·达拉斯·霍华德",
      "文森特·多诺费奥",
      "泰·辛普金斯",
      "尼克·罗宾森"
    ],
    "cover": "https://img3.doubanio.com/view/photo/s_ratio_poster/public/p2246217861.jpg",
    "id": "10440138",
    "cover_y": 2000
  },
  {
    "directors": [
      "托马斯·温特伯格"
    ],
    "rate": "9.1",
    "cover_x": 1433,
    "star": "45",
    "title": "狩猎",
    "url": "https://movie.douban.com/subject/6985810/",
    "casts": [
      "麦斯·米科尔森",
      "托玛斯·博·拉森",
      "安妮卡·韦德科普",
      "拉丝·弗格斯托姆",
      "苏西·沃德"
    ],
    "cover": "https://img1.doubanio.com/view/photo/s_ratio_poster/public/p1546987967.jpg",
    "id": "6985810",
    "cover_y": 2048
  },
  {
    "directors": [
      "罗伯·科恩"
    ],
    "rate": "7.8",
    "cover_x": 1000,
    "star": "40",
    "title": "速度与激情",
    "url": "https://movie.douban.com/subject/1304899/",
    "casts": [
      "范·迪塞尔",
      "保罗·沃克",
      "乔丹娜·布鲁斯特",
      "米歇尔·罗德里格兹",
      "尹成植"
    ],
    "cover": "https://img9.doubanio.com/view/photo/s_ratio_poster/public/p1033539605.jpg",
    "id": "1304899",
    "cover_y": 1500
  },
  {
    "directors": [
      "王家卫"
    ],
    "rate": "8.5",
    "cover_x": 2143,
    "star": "45",
    "title": "阿飞正传",
    "url": "https://movie.douban.com/subject/1305690/",
    "casts": [
      "张国荣",
      "张曼玉",
      "刘嘉玲",
      "刘德华",
      "张学友"
    ],
    "cover": "https://img3.doubanio.com/view/photo/s_ratio_poster/public/p2525770523.jpg",
    "id": "1305690",
    "cover_y": 2993
  },
  {
    "directors": [
      "安东尼·琼"
    ],
    "rate": "9.1",
    "cover_x": 2703,
    "star": "45",
    "title": "外星也难民 第一季",
    "url": "https://movie.douban.com/subject/30312909/",
    "casts": [
      "贾斯汀·罗兰",
      "托马斯·米德蒂奇",
      "肖恩·吉布朗尼",
      "玛丽·麦克",
      "安德鲁·达利"
    ],
    "cover": "https://img3.doubanio.com/view/photo/s_ratio_poster/public/p2600469202.jpg",
    "id": "30312909",
    "cover_y": 4004
  },
  {
    "directors": [
      "罗兰·艾默里奇"
    ],
    "rate": "8.2",
    "cover_x": 1359,
    "star": "40",
    "title": "后天",
    "url": "https://movie.douban.com/subject/1308779/",
    "casts": [
      "丹尼斯·奎德",
      "杰克·吉伦哈尔",
      "埃米·罗森",
      "达什·米霍克",
      "杰伊·桑德斯"
    ],
    "cover": "https://img1.doubanio.com/view/photo/s_ratio_poster/public/p2209602029.jpg",
    "id": "1308779",
    "cover_y": 1986
  },
  {
    "directors": [
      "不思凡"
    ],
    "rate": "7.8",
    "cover_x": 1080,
    "star": "40",
    "title": "大护法",
    "url": "https://movie.douban.com/subject/26811587/",
    "casts": [
      "小连杀",
      "图特哈蒙",
      "金士杰",
      "幽舞越山",
      "李佳怡"
    ],
    "cover": "https://img1.doubanio.com/view/photo/s_ratio_poster/public/p2490948849.jpg",
    "id": "26811587",
    "cover_y": 1760
  },
  {
    "directors": [
      "派蒂·杰金斯"
    ],
    "rate": "7.1",
    "cover_x": 2000,
    "star": "35",
    "title": "神奇女侠",
    "url": "https://movie.douban.com/subject/1578714/",
    "casts": [
      "盖尔·加朵",
      "克里斯·派恩",
      "康妮·尼尔森",
      "罗宾·怀特",
      "丹尼·赫斯顿"
    ],
    "cover": "https://img3.doubanio.com/view/photo/s_ratio_poster/public/p2460006593.jpg",
    "id": "1578714",
    "cover_y": 2857
  },
  {
    "directors": [
      "詹姆斯·曼高德"
    ],
    "rate": "8.6",
    "cover_x": 2977,
    "star": "45",
    "title": "极速车王",
    "url": "https://movie.douban.com/subject/6538866/",
    "casts": [
      "马特·达蒙",
      "克里斯蒂安·贝尔",
      "乔什·卢卡斯",
      "乔·博恩瑟",
      "崔西·莱茨"
    ],
    "cover": "https://img3.doubanio.com/view/photo/s_ratio_poster/public/p2614997281.jpg",
    "id": "6538866",
    "cover_y": 4410
  },
  {
    "directors": [
      "今敏"
    ],
    "rate": "9.0",
    "cover_x": 2130,
    "star": "45",
    "title": "红辣椒",
    "url": "https://movie.douban.com/subject/1865703/",
    "casts": [
      "林原惠美",
      "江守彻",
      "堀胜之祐",
      "古谷彻",
      "大塚明夫"
    ],
    "cover": "https://img3.doubanio.com/view/photo/s_ratio_poster/public/p456825720.jpg",
    "id": "1865703",
    "cover_y": 3030
  },
  {
    "directors": [
      "曹保平"
    ],
    "rate": "7.8",
    "cover_x": 3500,
    "star": "40",
    "title": "追凶者也",
    "url": "https://movie.douban.com/subject/26284621/",
    "casts": [
      "刘烨",
      "张译",
      "段博文",
      "王子文",
      "谭卓"
    ],
    "cover": "https://img3.doubanio.com/view/photo/s_ratio_poster/public/p2375882763.jpg",
    "id": "26284621",
    "cover_y": 4898
  },
  {
    "directors": [
      "道格·里曼"
    ],
    "rate": "8.6",
    "cover_x": 1000,
    "star": "45",
    "title": "谍影重重",
    "url": "https://movie.douban.com/subject/1304102/",
    "casts": [
      "马特·达蒙",
      "弗朗卡·波滕特",
      "克里斯·库珀",
      "克莱夫·欧文",
      "朱丽娅·斯蒂尔斯"
    ],
    "cover": "https://img3.doubanio.com/view/photo/s_ratio_poster/public/p1597183981.jpg",
    "id": "1304102",
    "cover_y": 1500
  },
  {
    "directors": [
      "杨洁"
    ],
    "rate": "9.6",
    "cover_x": 1200,
    "star": "50",
    "title": "西游记",
    "url": "https://movie.douban.com/subject/2156663/",
    "casts": [
      "六小龄童",
      "迟重瑞",
      "马德华",
      "汪粤",
      "徐少华"
    ],
    "cover": "https://img1.doubanio.com/view/photo/s_ratio_poster/public/p2265959269.jpg",
    "id": "2156663",
    "cover_y": 1655
  },
  {
    "directors": [
      "布拉德·伯德"
    ],
    "rate": "7.9",
    "cover_x": 1900,
    "star": "40",
    "title": "超人总动员2",
    "url": "https://movie.douban.com/subject/25849049/",
    "casts": [
      "格雷格·T·尼尔森",
      "霍利·亨特",
      "莎拉·沃威尔",
      "赫克·米尔纳",
      "伊莱·富西尔"
    ],
    "cover": "https://img3.doubanio.com/view/photo/s_ratio_poster/public/p2522880251.jpg",
    "id": "25849049",
    "cover_y": 2663
  }
]